pyawscp/Aws_Session.py
pyawscp/Config.py
pyawscp/CookieTempCredentials.py
pyawscp/CsvDrawIo.py
pyawscp/CsvDrawIoNetworking.py
pyawscp/DiagramMgnt.py
pyawscp/Emoticons.py
pyawscp/Functions.py
pyawscp/JustOneShot.py
pyawscp/PrettyTable.py
pyawscp/PyAsciiGraphs.py
pyawscp/PyAwsShell.py
pyawscp/PyEc2Cp.py
pyawscp/PyEc2NetSecCp.py
pyawscp/PyElbCp.py
pyawscp/PyR53Cp.py
pyawscp/PyS3Cp.py
pyawscp/TableArgs.py
pyawscp/Utils.py
pyawscp/__init__.py
pyawscp/messages.py
pyawscp/pyawscp.py
pyawscp/testDiagram.py
pyawscp/testing.py
pyawscp/pymxgraph/HttpServer.py
pyawscp/pymxgraph/HttpServerServices.py
pyawscp/pymxgraph/HttpServerServicesMock.py
pyawscp/pymxgraph/PySocketClient.py
pyawscp/pymxgraph/PySocketServer.py
pyawscp/pymxgraph/PyWebSocketServer.py
pyawscp/pymxgraph/PymxGraph.py
pyawscp/pymxgraph/PymxGraphAwsNavigator.py
pyawscp/pymxgraph/PymxGraphTree.py
pyawscp/pymxgraph/localfile.html
pyawscp/pymxgraph/css/common.css
pyawscp/pymxgraph/css/explorer.css
pyawscp/pymxgraph/images/actor.gif
pyawscp/pymxgraph/images/alignbottom.gif
pyawscp/pymxgraph/images/aligncenter.gif
pyawscp/pymxgraph/images/alignleft.gif
pyawscp/pymxgraph/images/alignmiddle.gif
pyawscp/pymxgraph/images/alignright.gif
pyawscp/pymxgraph/images/aligntop.gif
pyawscp/pymxgraph/images/arrow.gif
pyawscp/pymxgraph/images/bell.png
pyawscp/pymxgraph/images/bg.gif
pyawscp/pymxgraph/images/block_end.gif
pyawscp/pymxgraph/images/block_start.gif
pyawscp/pymxgraph/images/bold.gif
pyawscp/pymxgraph/images/bottom.gif
pyawscp/pymxgraph/images/box.png
pyawscp/pymxgraph/images/button.gif
pyawscp/pymxgraph/images/camera.gif
pyawscp/pymxgraph/images/center.gif
pyawscp/pymxgraph/images/classic_end.gif
pyawscp/pymxgraph/images/classic_start.gif
pyawscp/pymxgraph/images/close.gif
pyawscp/pymxgraph/images/cloud.gif
pyawscp/pymxgraph/images/cmp-bg.gif
pyawscp/pymxgraph/images/collapse.gif
pyawscp/pymxgraph/images/collapsed.gif
pyawscp/pymxgraph/images/connect.gif
pyawscp/pymxgraph/images/connector.gif
pyawscp-0.6.11.dist-info/METADATA
pyawscp-0.6.11.dist-info/WHEEL
pyawscp-0.6.11.dist-info/entry_points.txt
pyawscp-0.6.11.dist-info/top_level.txt
pyawscp-0.6.11.dist-info/RECORD
