Metadata-Version: 2.1
Name: pyawscp
Version: 0.6.11
Summary: A simple 'Python Shell' environment that you can use to 'talk' with your AWS account...
Home-page: https://ualter.github.io/pyawscp/
Author: Ualter Otoni Pereira
Author-email: ualter.junior@gmail.com
License: MIT
Keywords: aws,cloud,drawio,boto3,ec2,vpc
Platform: UNKNOWN
Classifier: Development Status :: 3 - Alpha
Classifier: License :: OSI Approved :: MIT License
Classifier: Programming Language :: Python :: 3
Classifier: Programming Language :: Python :: 3.7
Requires-Dist: Pygments
Requires-Dist: XlsxWriter
Requires-Dist: arnparse
Requires-Dist: boto3 (>=1.14.2)
Requires-Dist: botocore (>=1.17.63)
Requires-Dist: clipboard
Requires-Dist: pyreadline
Requires-Dist: requests
Requires-Dist: svglib
Requires-Dist: tinydb
Requires-Dist: websockets
